{"golf": "0,10", "Boxing": "0,16", "Conservative": "-2,16", "DeepIntoYouTube": "1,31", "democrats": "-1,6", "relationships": "-3,64", "GlobalOffensive": "-2,17", "UIUC": "-2,15", "Showerthoughts": "0,21", "hockey": "0,21", "meirl": "1,48", "soccer": "-2,42", "uofm": "0,11", "Bowling": "1,4", "gifs": "-1,38", "Republican": "-2,9", "progressive": "-3,12", "nfl": "-1,37", "AskReddit": "0,16", "Libertarian": "-2,14", "cringe": "-3,47", "pokemongo": "0,11", "gaming": "-1,25", "NoMansSkyTheGame": "0,11", "nba": "-2,36", "depression": "1,6", "space": "0,19", "wow": "-2,18", "wikipedia": "-1,21", "socialism": "0,27", "olympics": "1,11", "leagueoflegends": "-1,17", "worldnews": "-3,21", "UVA": "1,10", "pcmasterrace": "0,12", "Astronomy": "0,14", "hillaryclinton": "-1,25", "uofmn": "1,9", "Cricket": "0,14", "NASCAR": "0,10", "baseball": "0,39", "berkeley": "-2,18", "news": "-3,23", "pics": "-1,30", "nosleep": "0,20", "UCSD": "-1,11", "VirginiaTech": "1,10", "SquaredCircle": "0,24", "todayilearned": "-1,34", "SubredditSimulator": "1,5", "AskHistorians": "0,34", "msu": "0,12", "tennis": "-1,13", "ucla": "0,8", "UCSantaBarbara": "0,9", "iphone": "0,12", "woahdude": "0,41", "gatech": "-1,17", "science": "-1,19", "tabletennis": "1,4", "movies": "-1,32", "rutgers": "0,8", "DotA2": "-1,18", "The_Donald": "0,33", "MMA": "-2,25", "history": "0,21", "formula1": "-1,28", "videos": "-1,32", "rit": "1,12", "gadgets": "-1,19", "engineering": "1,15", "politics": "-3,17", "technology": "-1,28", "Android": "0,23", "funny": "-1,34", "aggies": "-1,19", "travel": "1,8", "fantasyfootball": "-1,18", "RPI": "0,13", "Archery": "1,6", "Anarchism": "-1,17", "askscience": "1,15", "Futurology": "-1,14", "lacrosse": "1,7", "Overwatch": "-1,13", "volleyball": "1,6"}